webcordlib/__init__.py
webcordlib-0.1.2.dist-info/licenses/LICENSE
webcordlib-0.1.2.dist-info/METADATA
webcordlib-0.1.2.dist-info/WHEEL
webcordlib-0.1.2.dist-info/top_level.txt
webcordlib-0.1.2.dist-info/RECORD
