Metadata-Version: 2.4
Name: webcordlib
Version: 0.1.2
Summary: A simple lib to interact with Discord Webhooks
Author-email: Guillaume Plagier <ranswnry@gmail.com>
License-Expression: MIT
Requires-Python: >=3.9
License-File: LICENSE
Requires-Dist: requests
Dynamic: license-file
